narrative/__init__.py
narrative/py.typed
narrative-1.2.1.dist-info/LICENSE
narrative-1.2.1.dist-info/METADATA
narrative-1.2.1.dist-info/WHEEL
narrative-1.2.1.dist-info/RECORD
