Metadata-Version: 2.3
Name: narrative
Version: 1.2.1
Summary: A small Python package for splitting text into dialogue and narrative.
License: GPLv3
Author: David L. Day
Author-email: david@davidlday.com
Requires-Python: >=3.9,<4.0
Classifier: Development Status :: 5 - Production/Stable
Classifier: Intended Audience :: Developers
Classifier: Intended Audience :: Science/Research
Classifier: License :: OSI Approved :: GNU General Public License v3 (GPLv3)
Classifier: License :: Other/Proprietary License
Classifier: Natural Language :: English
Classifier: Operating System :: OS Independent
Classifier: Programming Language :: Python :: 3
Classifier: Programming Language :: Python :: 3.9
Classifier: Programming Language :: Python :: 3.10
Classifier: Programming Language :: Python :: 3.11
Classifier: Programming Language :: Python :: 3.12
Classifier: Programming Language :: Python :: 3.13
Classifier: Topic :: Software Development :: Libraries :: Python Modules
Classifier: Topic :: Text Processing :: Linguistic
Requires-Dist: importlib-metadata (>=5.1,<7.0)
Project-URL: Bug Tracker, https://github.com/prosegrinder/python-narrative/issues
Project-URL: Homepage, https://github.com/prosegrinder/python-narrative
Project-URL: Repository, https://github.com/prosegrinder/python-narrative
